livetimer/__init__.py
livetimer/timers.py
livetimer-0.2.0.dist-info/LICENSE
livetimer-0.2.0.dist-info/METADATA
livetimer-0.2.0.dist-info/WHEEL
livetimer-0.2.0.dist-info/RECORD
