Metadata-Version: 2.1
Name: LiveTimer
Version: 0.2.0
Summary: A Python module to log multiple points in a repeating operation to get live statistics.
Author: Wyko ter Haar
Author-email: wyko.ter.haar@gmail.com
Requires-Python: >=3.09,<4.0
Classifier: Programming Language :: Python :: 3
Classifier: Programming Language :: Python :: 3.9
Classifier: Programming Language :: Python :: 3.10
Classifier: Programming Language :: Python :: 3.11
Classifier: Programming Language :: Python :: 3.12
Requires-Dist: rich (>=13.8.1,<14.0.0)
